{
  "type": "TuningList",
  "file_path": "Graph2D/TuneData/IMH_Tuning_List_T_51.bin",
  "block": [
    {
      "id": 1,
      "entries": [
        {
          "title": "CC01_N00100_C51",
          "text": "どちらを使用する？"
        },
        {
          "title": "CC01_N00200_C51",
          "text": "ヘッドギア型を使用してみよう"
        },
        {
          "title": "CC01_N00300_C51",
          "text": "通常計測で調整しよう"
        },
        {
          "title": "CC01_N00400_C51",
          "text": "カプセルベッド型を使用してみよう"
        },
        {
          "title": "CC01_N00500_C51",
          "text": "精密計測で調整しよう"
        },
        {
          "title": "CC01_N00600_C51",
          "text": "計測はせずに調整しよう"
        },
        {
          "title": "CC01_N00700_C51",
          "text": "計測を開始するぞ\n\n"
        },
        {
          "title": "CC01_N00800_C51",
          "text": "計測は問題無いな\n\n"
        },
        {
          "title": "CC01_N00900_C51",
          "text": "計測は順調だ\n\n"
        },
        {
          "title": "CC01_N01000_C51",
          "text": "クリアな波形で計測できているな\n\n"
        },
        {
          "title": "クリアな波形で計測できているな\n\n",
          "text": "CC01_N00900_C51"
        },
        {
          "title": "少しノイズが出ているな\n\n",
          "text": "CC01_N01000_C51"
        },
        {
          "title": "波形が乱れているな\n\n",
          "text": "CC01_N01100_C51"
        },
        {
          "title": "CC01_N01400_C51",
          "text": "すまん\nもう一度計測させてほしい\n"
        },
        {
          "title": "CC01_N01500_C51",
          "text": "まずまずの計測結果だったぞ\n\n"
        },
        {
          "title": "CC01_N01600_C51",
          "text": "良い計測結果になったな\nこれなら調整も上手く行くと思うぞ\n"
        },
        {
          "title": "CC01_N01700_C51",
          "text": "すまない……\n調整に失敗してしまったよ\n"
        },
        {
          "title": "CC01_N01800_C51",
          "text": "調整はしてみたけど\nあまり変わりは出なかったな\n"
        },
        {
          "title": "CC01_N01900_C51",
          "text": "まずまずの調整結果だったぞ\nきっと効果も実感できるはずだ\n"
        },
        {
          "title": "CC01_N02000_C51",
          "text": "調整は上手くいったぞ\nかなり扱いやすくなったはずだ\n"
        }
      ]
    },
    {
      "id": 2,
      "entries": [
        {
          "title": "CC01_N00100_C51",
          "text": "どちらを使用する？"
        },
        {
          "title": "CC01_N00200_C51",
          "text": "ヘッドギア型を使用してみよう"
        },
        {
          "title": "CC01_N00300_C51",
          "text": "通常計測で調整しよう"
        },
        {
          "title": "CC01_N00400_C51",
          "text": "カプセルベッド型を使用してみよう"
        },
        {
          "title": "CC01_N00500_C51",
          "text": "精密計測で調整しよう"
        },
        {
          "title": "CC01_N00600_C51",
          "text": "計測はせずに調整しよう"
        },
        {
          "title": "CC04_N00700_C51",
          "text": "それじゃあ、司波さん\n計測を始めましょう\n"
        },
        {
          "title": "CC04_N00800_C51",
          "text": "計測は問題無いです\n\n"
        },
        {
          "title": "CC04_N00900_C51",
          "text": "順調に計測できています\n\n"
        },
        {
          "title": "CC04_N01000_C51",
          "text": "綺麗な波形だ……\n\n"
        },
        {
          "title": "綺麗な波形だ……\n\n",
          "text": "CC04_N00900_C51"
        },
        {
          "title": "少しノイズが出ていますね……\n\n",
          "text": "CC04_N01000_C51"
        },
        {
          "title": "波形に乱れが出ていますね\n気掛かりなことでも",
          "text": "CC04_N01100_C51"
        },
        {
          "title": "CC04_N01400_C51",
          "text": "すみません、司波さん\n後で再計測させてください\n"
        },
        {
          "title": "CC04_N01500_C51",
          "text": "司波さん、お疲れ様です\nまずまずの計測結果が取れました\n"
        },
        {
          "title": "CC04_N01600_C51",
          "text": "お疲れ様です、司波さん\n計測結果も良い数値が出ていますし\nこれなら調整も楽になります"
        },
        {
          "title": "CC04_N01700_C51",
          "text": "すみません、司波さん\nあまり良い調整になりませんでした\n"
        },
        {
          "title": "CC04_N01800_C51",
          "text": "調整はしてみましたが……\n司波さんには\n相応しくない出来になってしまいました"
        },
        {
          "title": "CC04_N01900_C51",
          "text": "問題無く、調整ができたと思います\n司波さんも\n十分に効果が実感できると思います"
        },
        {
          "title": "CC04_N02000_C51",
          "text": "調整は上手くいきました\n司波さんに相応しい物になったと思います\nどうでしょう？"
        }
      ]
    },
    {
      "id": 4,
      "entries": [
        {
          "title": "CC01_N00100_C51",
          "text": "どちらを使用する？"
        },
        {
          "title": "CC01_N00200_C51",
          "text": "ヘッドギア型を使用してみよう"
        },
        {
          "title": "CC01_N00300_C51",
          "text": "通常計測で調整しよう"
        },
        {
          "title": "CC01_N00400_C51",
          "text": "カプセルベッド型を使用してみよう"
        },
        {
          "title": "CC01_N00500_C51",
          "text": "精密計測で調整しよう"
        },
        {
          "title": "CC01_N00600_C51",
          "text": "計測はせずに調整しよう"
        },
        {
          "title": "CC01_N00700_C51",
          "text": "計測を開始するぞ\n\n"
        },
        {
          "title": "CC01_N00800_C51",
          "text": "計測は問題無いな\n\n"
        },
        {
          "title": "CC01_N00900_C51",
          "text": "計測は順調だ\n\n"
        },
        {
          "title": "CC01_N01000_C51",
          "text": "クリアな波形で計測できているな\n\n"
        },
        {
          "title": "クリアな波形で計測できているな\n\n",
          "text": "CC01_N00900_C51"
        },
        {
          "title": "少しノイズが出ているな\n\n",
          "text": "CC01_N01000_C51"
        },
        {
          "title": "波形が乱れているな\n\n",
          "text": "CC01_N01100_C51"
        },
        {
          "title": "CC01_N01400_C51",
          "text": "すまん\nもう一度計測させてほしい\n"
        },
        {
          "title": "CC01_N01500_C51",
          "text": "まずまずの計測結果だったぞ\n\n"
        },
        {
          "title": "CC01_N01600_C51",
          "text": "良い計測結果になったな\nこれなら調整も上手く行くと思うぞ\n"
        },
        {
          "title": "CC01_N01700_C51",
          "text": "すまない……\n調整に失敗してしまったよ\n"
        },
        {
          "title": "CC01_N01800_C51",
          "text": "調整はしてみたけど\nあまり変わりは出なかったな\n"
        },
        {
          "title": "CC01_N01900_C51",
          "text": "まずまずの調整結果だったぞ\nきっと効果も実感できるはずだ\n"
        },
        {
          "title": "CC01_N02000_C51",
          "text": "調整は上手くいったぞ\nかなり扱いやすくなったはずだ\n"
        }
      ]
    },
    {
      "id": 3,
      "entries": [
        {
          "title": "CC01_N00100_C51",
          "text": "どちらを使用する？"
        },
        {
          "title": "CC01_N00200_C51",
          "text": "ヘッドギア型を使用してみよう"
        },
        {
          "title": "CC01_N00300_C51",
          "text": "通常計測で調整しよう"
        },
        {
          "title": "CC01_N00400_C51",
          "text": "カプセルベッド型を使用してみよう"
        },
        {
          "title": "CC01_N00500_C51",
          "text": "精密計測で調整しよう"
        },
        {
          "title": "CC01_N00600_C51",
          "text": "計測はせずに調整しよう"
        },
        {
          "title": "CC01_N00700_C51",
          "text": "計測を開始するぞ\n\n"
        },
        {
          "title": "CC01_N00800_C51",
          "text": "計測は問題無いな\n\n"
        },
        {
          "title": "CC01_N00900_C51",
          "text": "計測は順調だ\n\n"
        },
        {
          "title": "CC01_N01000_C51",
          "text": "クリアな波形で計測できているな\n\n"
        },
        {
          "title": "クリアな波形で計測できているな\n\n",
          "text": "CC01_N00900_C51"
        },
        {
          "title": "少しノイズが出ているな\n\n",
          "text": "CC01_N01000_C51"
        },
        {
          "title": "波形が乱れているな\n\n",
          "text": "CC01_N01100_C51"
        },
        {
          "title": "CC01_N01400_C51",
          "text": "すまん\nもう一度計測させてほしい\n"
        },
        {
          "title": "CC01_N01500_C51",
          "text": "まずまずの計測結果だったぞ\n\n"
        },
        {
          "title": "CC01_N01600_C51",
          "text": "良い計測結果になったな\nこれなら調整も上手く行くと思うぞ\n"
        },
        {
          "title": "CC01_N01700_C51",
          "text": "すまない……\n調整に失敗してしまったよ\n"
        },
        {
          "title": "CC01_N01800_C51",
          "text": "調整はしてみたけど\nあまり変わりは出なかったな\n"
        },
        {
          "title": "CC01_N01900_C51",
          "text": "まずまずの調整結果だったぞ\nきっと効果も実感できるはずだ\n"
        },
        {
          "title": "CC01_N02000_C51",
          "text": "調整は上手くいったぞ\nかなり扱いやすくなったはずだ\n"
        }
      ]
    },
    {
      "id": 5,
      "entries": [
        {
          "title": "CC01_N00100_C51",
          "text": "どちらを使用する？"
        },
        {
          "title": "CC01_N00200_C51",
          "text": "ヘッドギア型を使用してみよう"
        },
        {
          "title": "CC01_N00300_C51",
          "text": "通常計測で調整しよう"
        },
        {
          "title": "CC01_N00400_C51",
          "text": "カプセルベッド型を使用してみよう"
        },
        {
          "title": "CC01_N00500_C51",
          "text": "精密計測で調整しよう"
        },
        {
          "title": "CC01_N00600_C51",
          "text": "計測はせずに調整しよう"
        },
        {
          "title": "CC01_N00700_C51",
          "text": "計測を開始するぞ\n\n"
        },
        {
          "title": "CC01_N00800_C51",
          "text": "計測は問題無いな\n\n"
        },
        {
          "title": "CC01_N00900_C51",
          "text": "計測は順調だ\n\n"
        },
        {
          "title": "CC01_N01000_C51",
          "text": "クリアな波形で計測できているな\n\n"
        },
        {
          "title": "クリアな波形で計測できているな\n\n",
          "text": "CC01_N00900_C51"
        },
        {
          "title": "少しノイズが出ているな\n\n",
          "text": "CC01_N01000_C51"
        },
        {
          "title": "波形が乱れているな\n\n",
          "text": "CC01_N01100_C51"
        },
        {
          "title": "CC01_N01400_C51",
          "text": "すまん\nもう一度計測させてほしい\n"
        },
        {
          "title": "CC01_N01500_C51",
          "text": "まずまずの計測結果だったぞ\n\n"
        },
        {
          "title": "CC01_N01600_C51",
          "text": "良い計測結果になったな\nこれなら調整も上手く行くと思うぞ\n"
        },
        {
          "title": "CC01_N01700_C51",
          "text": "すまない……\n調整に失敗してしまったよ\n"
        },
        {
          "title": "CC01_N01800_C51",
          "text": "調整はしてみたけど\nあまり変わりは出なかったな\n"
        },
        {
          "title": "CC01_N01900_C51",
          "text": "まずまずの調整結果だったぞ\nきっと効果も実感できるはずだ\n"
        },
        {
          "title": "CC01_N02000_C51",
          "text": "調整は上手くいったぞ\nかなり扱いやすくなったはずだ\n"
        }
      ]
    },
    {
      "id": 6,
      "entries": [
        {
          "title": "",
          "text": "どちらを使用する？"
        },
        {
          "title": "",
          "text": "ヘッドギア型を使用してみよう"
        },
        {
          "title": "",
          "text": "通常計測で調整しよう"
        },
        {
          "title": "",
          "text": "カプセルベッド型を使用してみよう"
        },
        {
          "title": "",
          "text": "精密計測で調整しよう"
        },
        {
          "title": "",
          "text": "計測はせずに調整しよう"
        },
        {
          "title": "",
          "text": "計測を開始するぞ\n\n"
        },
        {
          "title": "",
          "text": "計測は問題無いな\n\n"
        },
        {
          "title": "",
          "text": "計測は順調だ\n\n"
        },
        {
          "title": "",
          "text": "クリアな波形で計測できているな\n\n"
        },
        {
          "title": "クリアな波形で計測できているな\n\n",
          "text": ""
        },
        {
          "title": "少しノイズが出ているな\n\n",
          "text": ""
        },
        {
          "title": "波形が乱れているな\n\n",
          "text": ""
        },
        {
          "title": "",
          "text": "すまん\nもう一度計測させてほしい\n"
        },
        {
          "title": "",
          "text": "まずまずの計測結果だったぞ\n\n"
        },
        {
          "title": "",
          "text": "良い計測結果になったな\nこれなら調整も上手く行くと思うぞ\n"
        },
        {
          "title": "",
          "text": "すまない……\n調整に失敗してしまったよ\n"
        },
        {
          "title": "",
          "text": "調整はしてみたけど\nあまり変わりは出なかったな\n"
        },
        {
          "title": "",
          "text": "まずまずの調整結果だったぞ\nきっと効果も実感できるはずだ\n"
        },
        {
          "title": "",
          "text": "調整は上手くいったぞ\nかなり扱いやすくなったはずだ\n"
        }
      ]
    },
    {
      "id": 11,
      "entries": [
        {
          "title": "CC01_N00100_C51",
          "text": "どちらを使用する？"
        },
        {
          "title": "CC01_N00200_C51",
          "text": "ヘッドギア型を使用してみよう"
        },
        {
          "title": "CC01_N00300_C51",
          "text": "通常計測で調整しよう"
        },
        {
          "title": "CC01_N00400_C51",
          "text": "カプセルベッド型を使用してみよう"
        },
        {
          "title": "CC01_N00500_C51",
          "text": "精密計測で調整しよう"
        },
        {
          "title": "CC01_N00600_C51",
          "text": "計測はせずに調整しよう"
        },
        {
          "title": "CC01_N00700_C51",
          "text": "計測を開始するぞ\n\n"
        },
        {
          "title": "CC01_N00800_C51",
          "text": "計測は問題無いな\n\n"
        },
        {
          "title": "CC01_N00900_C51",
          "text": "計測は順調だ\n\n"
        },
        {
          "title": "CC01_N01000_C51",
          "text": "クリアな波形で計測できているな\n\n"
        },
        {
          "title": "クリアな波形で計測できているな\n\n",
          "text": "CC01_N00900_C51"
        },
        {
          "title": "少しノイズが出ているな\n\n",
          "text": "CC01_N01000_C51"
        },
        {
          "title": "波形が乱れているな\n\n",
          "text": "CC01_N01100_C51"
        },
        {
          "title": "CC01_N01400_C51",
          "text": "すまん\nもう一度計測させてほしい\n"
        },
        {
          "title": "CC01_N01500_C51",
          "text": "まずまずの計測結果だったぞ\n\n"
        },
        {
          "title": "CC01_N01600_C51",
          "text": "良い計測結果になったな\nこれなら調整も上手く行くと思うぞ\n"
        },
        {
          "title": "CC01_N01700_C51",
          "text": "すまない……\n調整に失敗してしまったよ\n"
        },
        {
          "title": "CC01_N01800_C51",
          "text": "調整はしてみたけど\nあまり変わりは出なかったな\n"
        },
        {
          "title": "CC01_N01900_C51",
          "text": "まずまずの調整結果だったぞ\nきっと効果も実感できるはずだ\n"
        },
        {
          "title": "CC01_N02000_C51",
          "text": "調整は上手くいったぞ\nかなり扱いやすくなったはずだ\n"
        }
      ]
    },
    {
      "id": 12,
      "entries": [
        {
          "title": "CC01_N00100_C51",
          "text": "どちらを使用する？"
        },
        {
          "title": "CC01_N00200_C51",
          "text": "ヘッドギア型を使用してみよう"
        },
        {
          "title": "CC01_N00300_C51",
          "text": "通常計測で調整しよう"
        },
        {
          "title": "CC01_N00400_C51",
          "text": "カプセルベッド型を使用してみよう"
        },
        {
          "title": "CC01_N00500_C51",
          "text": "精密計測で調整しよう"
        },
        {
          "title": "CC01_N00600_C51",
          "text": "計測はせずに調整しよう"
        },
        {
          "title": "CC01_N00700_C51",
          "text": "計測を開始するぞ\n\n"
        },
        {
          "title": "CC01_N00800_C51",
          "text": "計測は問題無いな\n\n"
        },
        {
          "title": "CC01_N00900_C51",
          "text": "計測は順調だ\n\n"
        },
        {
          "title": "CC01_N01000_C51",
          "text": "クリアな波形で計測できているな\n\n"
        },
        {
          "title": "クリアな波形で計測できているな\n\n",
          "text": "CC01_N00900_C51"
        },
        {
          "title": "少しノイズが出ているな\n\n",
          "text": "CC01_N01000_C51"
        },
        {
          "title": "波形が乱れているな\n\n",
          "text": "CC01_N01100_C51"
        },
        {
          "title": "CC01_N01400_C51",
          "text": "すまん\nもう一度計測させてほしい\n"
        },
        {
          "title": "CC01_N01500_C51",
          "text": "まずまずの計測結果だったぞ\n\n"
        },
        {
          "title": "CC01_N01600_C51",
          "text": "良い計測結果になったな\nこれなら調整も上手く行くと思うぞ\n"
        },
        {
          "title": "CC01_N01700_C51",
          "text": "すまない……\n調整に失敗してしまったよ\n"
        },
        {
          "title": "CC01_N01800_C51",
          "text": "調整はしてみたけど\nあまり変わりは出なかったな\n"
        },
        {
          "title": "CC01_N01900_C51",
          "text": "まずまずの調整結果だったぞ\nきっと効果も実感できるはずだ\n"
        },
        {
          "title": "CC01_N02000_C51",
          "text": "調整は上手くいったぞ\nかなり扱いやすくなったはずだ\n"
        }
      ]
    },
    {
      "id": 14,
      "entries": [
        {
          "title": "CC01_N00100_C51",
          "text": "どちらを使用する？"
        },
        {
          "title": "CC01_N00200_C51",
          "text": "ヘッドギア型を使用してみよう"
        },
        {
          "title": "CC01_N00300_C51",
          "text": "通常計測で調整しよう"
        },
        {
          "title": "CC01_N00400_C51",
          "text": "カプセルベッド型を使用してみよう"
        },
        {
          "title": "CC01_N00500_C51",
          "text": "精密計測で調整しよう"
        },
        {
          "title": "CC01_N00600_C51",
          "text": "計測はせずに調整しよう"
        },
        {
          "title": "CC01_N00700_C51",
          "text": "計測を開始するぞ\n\n"
        },
        {
          "title": "CC01_N00800_C51",
          "text": "計測は問題無いな\n\n"
        },
        {
          "title": "CC01_N00900_C51",
          "text": "計測は順調だ\n\n"
        },
        {
          "title": "CC01_N01000_C51",
          "text": "クリアな波形で計測できているな\n\n"
        },
        {
          "title": "クリアな波形で計測できているな\n\n",
          "text": "CC01_N00900_C51"
        },
        {
          "title": "少しノイズが出ているな\n\n",
          "text": "CC01_N01000_C51"
        },
        {
          "title": "波形が乱れているな\n\n",
          "text": "CC01_N01100_C51"
        },
        {
          "title": "CC01_N01400_C51",
          "text": "すまん\nもう一度計測させてほしい\n"
        },
        {
          "title": "CC01_N01500_C51",
          "text": "まずまずの計測結果だったぞ\n\n"
        },
        {
          "title": "CC01_N01600_C51",
          "text": "良い計測結果になったな\nこれなら調整も上手く行くと思うぞ\n"
        },
        {
          "title": "CC01_N01700_C51",
          "text": "すまない……\n調整に失敗してしまったよ\n"
        },
        {
          "title": "CC01_N01800_C51",
          "text": "調整はしてみたけど\nあまり変わりは出なかったな\n"
        },
        {
          "title": "CC01_N01900_C51",
          "text": "まずまずの調整結果だったぞ\nきっと効果も実感できるはずだ\n"
        },
        {
          "title": "CC01_N02000_C51",
          "text": "調整は上手くいったぞ\nかなり扱いやすくなったはずだ\n"
        }
      ]
    },
    {
      "id": 21,
      "entries": [
        {
          "title": "CC01_N00100_C51",
          "text": "どちらを使用する？"
        },
        {
          "title": "CC01_N00200_C51",
          "text": "ヘッドギア型を使用してみよう"
        },
        {
          "title": "CC01_N00300_C51",
          "text": "通常計測で調整しよう"
        },
        {
          "title": "CC01_N00400_C51",
          "text": "カプセルベッド型を使用してみよう"
        },
        {
          "title": "CC01_N00500_C51",
          "text": "精密計測で調整しよう"
        },
        {
          "title": "CC01_N00600_C51",
          "text": "計測はせずに調整しよう"
        },
        {
          "title": "CC02_N00700_C51",
          "text": "計測を開始します\n\n"
        },
        {
          "title": "CC02_N00800_C51",
          "text": "計測に問題ありません\n\n"
        },
        {
          "title": "CC02_N00900_C51",
          "text": "計測は順調です\n\n"
        },
        {
          "title": "CC02_N01000_C51",
          "text": "クリアな波形で計測できています\n\n"
        },
        {
          "title": "クリアな波形で計測できています\n\n",
          "text": "CC02_N00900_C51"
        },
        {
          "title": "少しノイズが出ています\n\n",
          "text": "CC02_N01000_C51"
        },
        {
          "title": "波形が乱れています\n\n",
          "text": "CC02_N01100_C51"
        },
        {
          "title": "CC02_N01400_C51",
          "text": "すみません\n再計測が必要かと思います\n"
        },
        {
          "title": "CC02_N01500_C51",
          "text": "お疲れ様です\nまずまずの計測結果だと思います\n"
        },
        {
          "title": "CC02_N01600_C51",
          "text": "お疲れ様です\nこの結果なら調整もし易いと思います\n"
        },
        {
          "title": "CC02_N01700_C51",
          "text": "すみません\nあまり良い調整になりませんでした\n"
        },
        {
          "title": "CC02_N01800_C51",
          "text": "調整はしてみましたが\n大きな変化は出ませんでした\n"
        },
        {
          "title": "CC02_N01900_C51",
          "text": "問題無く、調整ができたと思います\n効果も確認してみてください\n"
        },
        {
          "title": "CC02_N02000_C51",
          "text": "調整は上手くいきました\nかなり扱いやすくなったと思います\n"
        }
      ]
    },
    {
      "id": 22,
      "entries": [
        {
          "title": "",
          "text": "どちらを使用する？"
        },
        {
          "title": "",
          "text": "ヘッドギア型を使用してみよう"
        },
        {
          "title": "",
          "text": "通常計測で調整しよう"
        },
        {
          "title": "",
          "text": "カプセルベッド型を使用してみよう"
        },
        {
          "title": "",
          "text": "精密計測で調整しよう"
        },
        {
          "title": "",
          "text": "計測はせずに調整しよう"
        },
        {
          "title": "",
          "text": "計測を開始します\n\n"
        },
        {
          "title": "",
          "text": "計測に問題ありません\n\n"
        },
        {
          "title": "",
          "text": "計測は順調です\n\n"
        },
        {
          "title": "",
          "text": "クリアな波形で計測できています\n\n"
        },
        {
          "title": "クリアな波形で計測できています\n\n",
          "text": ""
        },
        {
          "title": "少しノイズが出ています\n\n",
          "text": ""
        },
        {
          "title": "波形が乱れています\n\n",
          "text": ""
        },
        {
          "title": "",
          "text": "すみません\n再計測が必要かと思います\n"
        },
        {
          "title": "",
          "text": "お疲れ様です\nまずまずの計測結果だと思います\n"
        },
        {
          "title": "",
          "text": "お疲れ様です\nこの結果なら調整もし易いと思います\n"
        },
        {
          "title": "",
          "text": "すみません\nあまり良い調整になりませんでした\n"
        },
        {
          "title": "",
          "text": "調整はしてみましたが\n大きな変化は出ませんでした\n"
        },
        {
          "title": "",
          "text": "問題無く、調整ができたと思います\n効果も確認してみてください\n"
        },
        {
          "title": "",
          "text": "調整は上手くいきました\nかなり扱いやすくなったと思います\n"
        }
      ]
    },
    {
      "id": 23,
      "entries": [
        {
          "title": "",
          "text": "どちらを使用する？"
        },
        {
          "title": "",
          "text": "ヘッドギア型を使用してみよう"
        },
        {
          "title": "",
          "text": "通常計測で調整しよう"
        },
        {
          "title": "",
          "text": "カプセルベッド型を使用してみよう"
        },
        {
          "title": "",
          "text": "精密計測で調整しよう"
        },
        {
          "title": "",
          "text": "計測はせずに調整しよう"
        },
        {
          "title": "",
          "text": "計測を開始します\n\n"
        },
        {
          "title": "",
          "text": "計測に問題ありません\n\n"
        },
        {
          "title": "",
          "text": "計測は順調です\n\n"
        },
        {
          "title": "",
          "text": "クリアな波形で計測できています\n\n"
        },
        {
          "title": "クリアな波形で計測できています\n\n",
          "text": ""
        },
        {
          "title": "少しノイズが出ています\n\n",
          "text": ""
        },
        {
          "title": "波形が乱れています\n\n",
          "text": ""
        },
        {
          "title": "",
          "text": "すみません\n再計測が必要かと思います\n"
        },
        {
          "title": "",
          "text": "お疲れ様です\nまずまずの計測結果だと思います\n"
        },
        {
          "title": "",
          "text": "お疲れ様です\nこの結果なら調整もし易いと思います\n"
        },
        {
          "title": "",
          "text": "すみません\nあまり良い調整になりませんでした\n"
        },
        {
          "title": "",
          "text": "調整はしてみましたが\n大きな変化は出ませんでした\n"
        },
        {
          "title": "",
          "text": "問題無く、調整ができたと思います\n効果も確認してみてください\n"
        },
        {
          "title": "",
          "text": "調整は上手くいきました\nかなり扱いやすくなったと思います\n"
        }
      ]
    },
    {
      "id": 29,
      "entries": [
        {
          "title": "CC01_N00100_C51",
          "text": "どちらを使用する？"
        },
        {
          "title": "CC01_N00200_C51",
          "text": "ヘッドギア型を使用してみよう"
        },
        {
          "title": "CC01_N00300_C51",
          "text": "通常計測で調整しよう"
        },
        {
          "title": "CC01_N00400_C51",
          "text": "カプセルベッド型を使用してみよう"
        },
        {
          "title": "CC01_N00500_C51",
          "text": "精密計測で調整しよう"
        },
        {
          "title": "CC01_N00600_C51",
          "text": "計測はせずに調整しよう"
        },
        {
          "title": "CC02_N00700_C51",
          "text": "計測を開始します\n\n"
        },
        {
          "title": "CC02_N00800_C51",
          "text": "計測に問題ありません\n\n"
        },
        {
          "title": "CC02_N00900_C51",
          "text": "計測は順調です\n\n"
        },
        {
          "title": "CC02_N01000_C51",
          "text": "クリアな波形で計測できています\n\n"
        },
        {
          "title": "クリアな波形で計測できています\n\n",
          "text": "CC02_N00900_C51"
        },
        {
          "title": "少しノイズが出ています\n\n",
          "text": "CC02_N01000_C51"
        },
        {
          "title": "波形が乱れています\n\n",
          "text": "CC02_N01100_C51"
        },
        {
          "title": "CC02_N01400_C51",
          "text": "すみません\n再計測が必要かと思います\n"
        },
        {
          "title": "CC02_N01500_C51",
          "text": "お疲れ様です\nまずまずの計測結果だと思います\n"
        },
        {
          "title": "CC02_N01600_C51",
          "text": "お疲れ様です\nこの結果なら調整もし易いと思います\n"
        },
        {
          "title": "CC02_N01700_C51",
          "text": "すみません\nあまり良い調整になりませんでした\n"
        },
        {
          "title": "CC02_N01800_C51",
          "text": "調整はしてみましたが\n大きな変化は出ませんでした\n"
        },
        {
          "title": "CC02_N01900_C51",
          "text": "問題無く、調整ができたと思います\n効果も確認してみてください\n"
        },
        {
          "title": "CC02_N02000_C51",
          "text": "調整は上手くいきました\nかなり扱いやすくなったと思います\n"
        }
      ]
    },
    {
      "id": 31,
      "entries": [
        {
          "title": "CC01_N00100_C51",
          "text": "どちらを使用する？"
        },
        {
          "title": "CC01_N00200_C51",
          "text": "ヘッドギア型を使用してみよう"
        },
        {
          "title": "CC01_N00300_C51",
          "text": "通常計測で調整しよう"
        },
        {
          "title": "CC01_N00400_C51",
          "text": "カプセルベッド型を使用してみよう"
        },
        {
          "title": "CC01_N00500_C51",
          "text": "精密計測で調整しよう"
        },
        {
          "title": "CC01_N00600_C51",
          "text": "計測はせずに調整しよう"
        },
        {
          "title": "CC02_N00700_C51",
          "text": "計測を開始します\n\n"
        },
        {
          "title": "CC02_N00800_C51",
          "text": "計測に問題ありません\n\n"
        },
        {
          "title": "CC02_N00900_C51",
          "text": "計測は順調です\n\n"
        },
        {
          "title": "CC02_N01000_C51",
          "text": "クリアな波形で計測できています\n\n"
        },
        {
          "title": "クリアな波形で計測できています\n\n",
          "text": "CC02_N00900_C51"
        },
        {
          "title": "少しノイズが出ています\n\n",
          "text": "CC02_N01000_C51"
        },
        {
          "title": "波形が乱れています\n\n",
          "text": "CC02_N01100_C51"
        },
        {
          "title": "CC02_N01400_C51",
          "text": "すみません\n再計測が必要かと思います\n"
        },
        {
          "title": "CC02_N01500_C51",
          "text": "お疲れ様です\nまずまずの計測結果だと思います\n"
        },
        {
          "title": "CC02_N01600_C51",
          "text": "お疲れ様です\nこの結果なら調整もし易いと思います\n"
        },
        {
          "title": "CC02_N01700_C51",
          "text": "すみません\nあまり良い調整になりませんでした\n"
        },
        {
          "title": "CC02_N01800_C51",
          "text": "調整はしてみましたが\n大きな変化は出ませんでした\n"
        },
        {
          "title": "CC02_N01900_C51",
          "text": "問題無く、調整ができたと思います\n効果も確認してみてください\n"
        },
        {
          "title": "CC02_N02000_C51",
          "text": "調整は上手くいきました\nかなり扱いやすくなったと思います\n"
        }
      ]
    },
    {
      "id": 34,
      "entries": [
        {
          "title": "CC01_N00100_C51",
          "text": "どちらを使用する？"
        },
        {
          "title": "CC01_N00200_C51",
          "text": "ヘッドギア型を使用してみよう"
        },
        {
          "title": "CC01_N00300_C51",
          "text": "通常計測で調整しよう"
        },
        {
          "title": "CC01_N00400_C51",
          "text": "カプセルベッド型を使用してみよう"
        },
        {
          "title": "CC01_N00500_C51",
          "text": "精密計測で調整しよう"
        },
        {
          "title": "CC01_N00600_C51",
          "text": "計測はせずに調整しよう"
        },
        {
          "title": "CC02_N00700_C51",
          "text": "計測を開始します\n\n"
        },
        {
          "title": "CC02_N00800_C51",
          "text": "計測に問題ありません\n\n"
        },
        {
          "title": "CC02_N00900_C51",
          "text": "計測は順調です\n\n"
        },
        {
          "title": "CC02_N01000_C51",
          "text": "クリアな波形で計測できています\n\n"
        },
        {
          "title": "クリアな波形で計測できています\n\n",
          "text": "CC02_N00900_C51"
        },
        {
          "title": "少しノイズが出ています\n\n",
          "text": "CC02_N01000_C51"
        },
        {
          "title": "波形が乱れています\n\n",
          "text": "CC02_N01100_C51"
        },
        {
          "title": "CC02_N01400_C51",
          "text": "すみません\n再計測が必要かと思います\n"
        },
        {
          "title": "CC02_N01500_C51",
          "text": "お疲れ様です\nまずまずの計測結果だと思います\n"
        },
        {
          "title": "CC02_N01600_C51",
          "text": "お疲れ様です\nこの結果なら調整もし易いと思います\n"
        },
        {
          "title": "CC02_N01700_C51",
          "text": "すみません\nあまり良い調整になりませんでした\n"
        },
        {
          "title": "CC02_N01800_C51",
          "text": "調整はしてみましたが\n大きな変化は出ませんでした\n"
        },
        {
          "title": "CC02_N01900_C51",
          "text": "問題無く、調整ができたと思います\n効果も確認してみてください\n"
        },
        {
          "title": "CC02_N02000_C51",
          "text": "調整は上手くいきました\nかなり扱いやすくなったと思います\n"
        }
      ]
    },
    {
      "id": 43,
      "entries": [
        {
          "title": "",
          "text": "どちらを使用する？"
        },
        {
          "title": "",
          "text": "ヘッドギア型を使用してみよう"
        },
        {
          "title": "",
          "text": "通常計測で調整しよう"
        },
        {
          "title": "",
          "text": "カプセルベッド型を使用してみよう"
        },
        {
          "title": "",
          "text": "精密計測で調整しよう"
        },
        {
          "title": "",
          "text": "計測はせずに調整しよう"
        },
        {
          "title": "",
          "text": "計測を開始します\n\n"
        },
        {
          "title": "",
          "text": "計測に問題ありません\n\n"
        },
        {
          "title": "",
          "text": "計測は順調です\n\n"
        },
        {
          "title": "",
          "text": "クリアな波形で計測できています\n\n"
        },
        {
          "title": "クリアな波形で計測できています\n\n",
          "text": ""
        },
        {
          "title": "少しノイズが出ています\n\n",
          "text": ""
        },
        {
          "title": "波形が乱れています\n\n",
          "text": ""
        },
        {
          "title": "",
          "text": "すみません\n再計測が必要かと思います\n"
        },
        {
          "title": "",
          "text": "お疲れ様です\nまずまずの計測結果だと思います\n"
        },
        {
          "title": "",
          "text": "お疲れ様です\nこの結果なら調整もし易いと思います\n"
        },
        {
          "title": "",
          "text": "すみません\nあまり良い調整になりませんでした\n"
        },
        {
          "title": "",
          "text": "調整はしてみましたが\n大きな変化は出ませんでした\n"
        },
        {
          "title": "",
          "text": "問題無く、調整ができたと思います\n効果も確認してみてください\n"
        },
        {
          "title": "",
          "text": "調整は上手くいきました\nかなり扱いやすくなったと思います\n"
        }
      ]
    },
    {
      "id": 51,
      "entries": [
        {
          "title": "",
          "text": "どちらを使用する？"
        },
        {
          "title": "",
          "text": "ヘッドギア型を使用してみよう"
        },
        {
          "title": "",
          "text": "通常計測で調整しよう"
        },
        {
          "title": "",
          "text": "カプセルベッド型を使用してみよう"
        },
        {
          "title": "",
          "text": "精密計測で調整しよう"
        },
        {
          "title": "",
          "text": "計測はせずに調整しよう"
        },
        {
          "title": "",
          "text": "計測を開始するぞ\n\n"
        },
        {
          "title": "",
          "text": "計測は問題無いな\n\n"
        },
        {
          "title": "",
          "text": "計測は順調だ\n\n"
        },
        {
          "title": "",
          "text": "クリアな波形で計測できているな\n\n"
        },
        {
          "title": "クリアな波形で計測できているな\n\n",
          "text": ""
        },
        {
          "title": "少しノイズが出ているな\n\n",
          "text": ""
        },
        {
          "title": "波形が乱れているな\n\n",
          "text": ""
        },
        {
          "title": "",
          "text": "すまん\nもう一度計測させてほしい\n"
        },
        {
          "title": "",
          "text": "まずまずの計測結果だったぞ\n\n"
        },
        {
          "title": "",
          "text": "良い計測結果になったな\nこれなら調整も上手く行くと思うぞ\n"
        },
        {
          "title": "",
          "text": "すまない……\n調整に失敗してしまったよ\n"
        },
        {
          "title": "",
          "text": "調整はしてみたけど\nあまり変わりは出なかったな\n"
        },
        {
          "title": "",
          "text": "まずまずの調整結果だったぞ\nきっと効果も実感できるはずだ\n"
        },
        {
          "title": "",
          "text": "調整は上手くいったぞ\nかなり扱いやすくなったはずだ\n"
        }
      ]
    },
    {
      "id": 52,
      "entries": [
        {
          "title": "",
          "text": "どちらを使用する？"
        },
        {
          "title": "",
          "text": "ヘッドギア型を使用してみよう"
        },
        {
          "title": "",
          "text": "通常計測で調整しよう"
        },
        {
          "title": "",
          "text": "カプセルベッド型を使用してみよう"
        },
        {
          "title": "",
          "text": "精密計測で調整しよう"
        },
        {
          "title": "",
          "text": "計測はせずに調整しよう"
        },
        {
          "title": "",
          "text": "計測を開始するぞ\n\n"
        },
        {
          "title": "",
          "text": "計測は問題無いな\n\n"
        },
        {
          "title": "",
          "text": "計測は順調だ\n\n"
        },
        {
          "title": "",
          "text": "クリアな波形で計測できているな\n\n"
        },
        {
          "title": "クリアな波形で計測できているな\n\n",
          "text": ""
        },
        {
          "title": "少しノイズが出ているな\n\n",
          "text": ""
        },
        {
          "title": "波形が乱れているな\n\n",
          "text": ""
        },
        {
          "title": "",
          "text": "すまん\nもう一度計測させてほしい\n"
        },
        {
          "title": "",
          "text": "まずまずの計測結果だったぞ\n\n"
        },
        {
          "title": "",
          "text": "良い計測結果になったな\nこれなら調整も上手く行くと思うぞ\n"
        },
        {
          "title": "",
          "text": "すまない……\n調整に失敗してしまったよ\n"
        },
        {
          "title": "",
          "text": "調整はしてみたけど\nあまり変わりは出なかったな\n"
        },
        {
          "title": "",
          "text": "まずまずの調整結果だったぞ\nきっと効果も実感できるはずだ\n"
        },
        {
          "title": "",
          "text": "調整は上手くいったぞ\nかなり扱いやすくなったはずだ\n"
        }
      ]
    },
    {
      "id": 81,
      "entries": [
        {
          "title": "CC01_N00100_C51",
          "text": "どちらを使用する？"
        },
        {
          "title": "CC01_N00200_C51",
          "text": "ヘッドギア型を使用してみよう"
        },
        {
          "title": "CC01_N00300_C51",
          "text": "通常計測で調整しよう"
        },
        {
          "title": "CC01_N00400_C51",
          "text": "カプセルベッド型を使用してみよう"
        },
        {
          "title": "CC01_N00500_C51",
          "text": "精密計測で調整しよう"
        },
        {
          "title": "CC01_N00600_C51",
          "text": "計測はせずに調整しよう"
        },
        {
          "title": "CC01_N00700_C51",
          "text": "計測を開始するぞ\n\n"
        },
        {
          "title": "CC01_N00800_C51",
          "text": "計測は問題無いな\n\n"
        },
        {
          "title": "CC01_N00900_C51",
          "text": "計測は順調だ\n\n"
        },
        {
          "title": "CC01_N01000_C51",
          "text": "クリアな波形で計測できているな\n\n"
        },
        {
          "title": "クリアな波形で計測できているな\n\n",
          "text": "CC01_N00900_C51"
        },
        {
          "title": "少しノイズが出ているな\n\n",
          "text": "CC01_N01000_C51"
        },
        {
          "title": "波形が乱れているな\n\n",
          "text": "CC01_N01100_C51"
        },
        {
          "title": "CC01_N01400_C51",
          "text": "すまん\nもう一度計測させてほしい\n"
        },
        {
          "title": "CC01_N01500_C51",
          "text": "まずまずの計測結果だったぞ\n\n"
        },
        {
          "title": "CC01_N01600_C51",
          "text": "良い計測結果になったな\nこれなら調整も上手く行くと思うぞ\n"
        },
        {
          "title": "CC01_N01700_C51",
          "text": "すまない……\n調整に失敗してしまったよ\n"
        },
        {
          "title": "CC01_N01800_C51",
          "text": "調整はしてみたけど\nあまり変わりは出なかったな\n"
        },
        {
          "title": "CC01_N01900_C51",
          "text": "まずまずの調整結果だったぞ\nきっと効果も実感できるはずだ\n"
        },
        {
          "title": "CC01_N02000_C51",
          "text": "調整は上手くいったぞ\nかなり扱いやすくなったはずだ\n"
        }
      ]
    },
    {
      "id": 91,
      "entries": [
        {
          "title": "CC01_N00100_C51",
          "text": "どちらを使用する？"
        },
        {
          "title": "CC01_N00200_C51",
          "text": "ヘッドギア型を使用してみよう"
        },
        {
          "title": "CC01_N00300_C51",
          "text": "通常計測で調整しよう"
        },
        {
          "title": "CC01_N00400_C51",
          "text": "カプセルベッド型を使用してみよう"
        },
        {
          "title": "CC01_N00500_C51",
          "text": "精密計測で調整しよう"
        },
        {
          "title": "CC01_N00600_C51",
          "text": "計測はせずに調整しよう"
        },
        {
          "title": "CC03_N00700_C51",
          "text": "計測を開始しよう\n\n"
        },
        {
          "title": "CC01_N00800_C51",
          "text": "計測は問題無いな\n\n"
        },
        {
          "title": "CC01_N00900_C51",
          "text": "計測は順調だ\n\n"
        },
        {
          "title": "CC01_N01000_C51",
          "text": "クリアな波形で計測できているな\n\n"
        },
        {
          "title": "クリアな波形で計測できているな\n\n",
          "text": "CC01_N00900_C51"
        },
        {
          "title": "少しノイズが出ているな\n\n",
          "text": "CC01_N01000_C51"
        },
        {
          "title": "波形が乱れているな\n\n",
          "text": "CC01_N01100_C51"
        },
        {
          "title": "CC03_N01400_C51",
          "text": "すまない\n後で再計測させてくれ\n"
        },
        {
          "title": "CC03_N01500_C51",
          "text": "まずまずの計測結果だろう\n\n"
        },
        {
          "title": "CC03_N01600_C51",
          "text": "良い計測結果になったよ\n\n"
        },
        {
          "title": "CC03_N01700_C51",
          "text": "……調整に失敗したか\n\n"
        },
        {
          "title": "CC01_N01800_C51",
          "text": "調整はしてみたけど\nあまり変わりは出なかったな\n"
        },
        {
          "title": "CC03_N01900_C51",
          "text": "まずまずの調整だったよ\n動作確認してみてくれ\n"
        },
        {
          "title": "CC03_N02000_C51",
          "text": "調整は上手くいったよ\nかなり性能は上がった筈だよ\n"
        }
      ]
    }
  ]
}