{
  "name": "evt000052_Txt.lua",
  "containers": [
    {
      "name": "t000001001",
      "lineContainers": [
        {
          "name": "name",
          "line": "司波　達也"
        },
        {
          "name": "txt",
          "lines": [
            "あっ待て\r\n",
            "深雪まだ……"
          ]
        },
        {
          "name": "voice",
          "line": "voe00000100100"
        }
      ]
    },
    {
      "name": "t000001002",
      "lineContainers": [
        {
          "name": "name",
          "line": "司波　深雪"
        },
        {
          "name": "voice",
          "line": "voe00000100200"
        }
      ]
    },
    {
      "name": "t000001003",
      "lineContainers": [
        {
          "name": "name",
          "line": "司波　達也"
        },
        {
          "name": "txt",
          "lines": [
            "すまない\r\n",
            "後調整をしていて\r\n",
            "席を外すのが遅くなった"
          ]
        },
        {
          "name": "voice",
          "line": "voe00000100300"
        }
      ]
    },
    {
      "name": "t000001004",
      "lineContainers": [
        {
          "name": "name",
          "line": "司波　深雪"
        },
        {
          "name": "txt",
          "lines": [
            "……お兄様\r\n",
            "わたしを見て\r\n",
            "何も感じませんか？"
          ]
        },
        {
          "name": "voice",
          "line": "voe00000100400"
        }
      ]
    },
    {
      "name": "t000001005",
      "lineContainers": [
        {
          "name": "name",
          "line": "司波　達也"
        },
        {
          "name": "txt",
          "lines": [
            "感じたらマズイだろう\r\n",
            "出て行くから早く着替えるんだ"
          ]
        },
        {
          "name": "voice",
          "line": "voe00000100500"
        }
      ]
    },
    {
      "name": "t000001006",
      "lineContainers": [
        {
          "name": "name",
          "line": "司波　深雪"
        },
        {
          "name": "txt",
          "lines": [
            "あっ\r\n",
            "もうっ\r\n",
            "お兄様ったら……"
          ]
        },
        {
          "name": "voice",
          "line": "voe00000100600"
        }
      ]
    },
    {
      "name": "t000002001",
      "lineContainers": [
        {
          "name": "name",
          "line": "千代田　花音"
        },
        {
          "name": "voice",
          "line": "voe00000200100"
        }
      ]
    },
    {
      "name": "t000002002",
      "lineContainers": [
        {
          "name": "name",
          "line": "五十里　啓"
        },
        {
          "name": "txt",
          "lines": [
            "えっ？\n",
            "何で出てきてるのっ！？"
          ]
        },
        {
          "name": "voice",
          "line": "voe00000200200"
        }
      ]
    },
    {
      "name": "t000002003",
      "lineContainers": [
        {
          "name": "name",
          "line": "千代田　花音"
        },
        {
          "name": "txt",
          "lines": [
            "どう？\n",
            "チョッとグッとくるでしょ？"
          ]
        },
        {
          "name": "voice",
          "line": "voe00000200300"
        }
      ]
    },
    {
      "name": "t000002004",
      "lineContainers": [
        {
          "name": "name",
          "line": "五十里　啓"
        },
        {
          "name": "txt",
          "lines": [
            "もうっ\r\n",
            "すぐ出てくから\r\n",
            "早く着替えて"
          ]
        },
        {
          "name": "voice",
          "line": "voe00000200400"
        }
      ]
    },
    {
      "name": "t000002005",
      "lineContainers": [
        {
          "name": "name",
          "line": "千代田　花音"
        },
        {
          "name": "txt",
          "lines": [
            "え～\r\n",
            "ちゃんと見てよ"
          ]
        },
        {
          "name": "voice",
          "line": "voe00000200500"
        }
      ]
    },
    {
      "name": "t000002006",
      "lineContainers": [
        {
          "name": "name",
          "line": "千代田　花音"
        },
        {
          "name": "voice",
          "line": "voe00000200600"
        }
      ]
    },
    {
      "name": "t000003001",
      "lineContainers": [
        {
          "name": "name",
          "line": "西城　レオンハルト"
        },
        {
          "name": "txt",
          "lines": [
            "あっ\r\n",
            "深雪さん待った！"
          ]
        },
        {
          "name": "voice",
          "line": "voe00000300100"
        }
      ]
    },
    {
      "name": "t000003002",
      "lineContainers": [
        {
          "name": "name",
          "line": "吉田　幹比古"
        },
        {
          "name": "txt",
          "lines": [
            "えっ\r\n",
            "深雪さん！？"
          ]
        },
        {
          "name": "voice",
          "line": "voe00000300200"
        }
      ]
    },
    {
      "name": "t000003003",
      "lineContainers": [
        {
          "name": "name",
          "line": "一条　将輝"
        },
        {
          "name": "txt",
          "lines": [
            "司波さん\r\n",
            "待って下さい！"
          ]
        },
        {
          "name": "voice",
          "line": "voe00000300300"
        }
      ]
    },
    {
      "name": "t000003004",
      "lineContainers": [
        {
          "name": "name",
          "line": "服部刑部少丞範蔵"
        },
        {
          "name": "txt",
          "lines": [
            "司波さん\r\n",
            "ダメだ！"
          ]
        },
        {
          "name": "voice",
          "line": "voe00000300400"
        }
      ]
    },
    {
      "name": "t000003005",
      "lineContainers": [
        {
          "name": "name",
          "line": "五十里　啓"
        },
        {
          "name": "txt",
          "lines": [
            "あっ\r\n",
            "司波さん\r\n",
            "まだっ！"
          ]
        },
        {
          "name": "voice",
          "line": "voe00000300500"
        }
      ]
    },
    {
      "name": "t000003006",
      "lineContainers": [
        {
          "name": "name",
          "line": "吉祥寺　真紅郎"
        },
        {
          "name": "txt",
          "lines": [
            "えっ\r\n",
            "まだ終わってな……！"
          ]
        },
        {
          "name": "voice",
          "line": "voe00000300600"
        }
      ]
    },
    {
      "name": "t000003007",
      "lineContainers": [
        {
          "name": "name",
          "line": "司波　深雪"
        },
        {
          "name": "voice",
          "line": "voe00000300700"
        }
      ]
    },
    {
      "name": "t000003008",
      "lineContainers": [
        {
          "name": "name",
          "line": "司波　深雪"
        },
        {
          "name": "txt",
          "lines": [
            "どうして\r\n",
            "いらっしゃるんですか？"
          ]
        },
        {
          "name": "voice",
          "line": "voe00000300800"
        }
      ]
    },
    {
      "name": "t000003009",
      "lineContainers": [
        {
          "name": "name",
          "line": "西城　レオンハルト"
        },
        {
          "name": "txt",
          "lines": [
            "あれっ今\r\n",
            "俺……？"
          ]
        },
        {
          "name": "voice",
          "line": "voe00000300900"
        }
      ]
    },
    {
      "name": "t000003010",
      "lineContainers": [
        {
          "name": "name",
          "line": "吉田　幹比古"
        },
        {
          "name": "txt",
          "lines": [
            "今何か\n",
            "恐ろしい目にあったような……"
          ]
        },
        {
          "name": "voice",
          "line": "voe00000301000"
        }
      ]
    },
    {
      "name": "t000003011",
      "lineContainers": [
        {
          "name": "name",
          "line": "一条　将輝"
        },
        {
          "name": "txt",
          "lines": [
            "んっ！？\r\n",
            "俺は何を……"
          ]
        },
        {
          "name": "voice",
          "line": "voe00000301100"
        }
      ]
    },
    {
      "name": "t000003012",
      "lineContainers": [
        {
          "name": "name",
          "line": "服部刑部少丞範蔵"
        },
        {
          "name": "voice",
          "line": "voe00000301200"
        }
      ]
    },
    {
      "name": "t000003013",
      "lineContainers": [
        {
          "name": "name",
          "line": "五十里　啓"
        },
        {
          "name": "txt",
          "lines": [
            "うんっ？\r\n",
            "あれっ？"
          ]
        },
        {
          "name": "voice",
          "line": "voe00000301300"
        }
      ]
    },
    {
      "name": "t000003014",
      "lineContainers": [
        {
          "name": "name",
          "line": "吉祥寺　真紅郎"
        },
        {
          "name": "voice",
          "line": "voe00000301400"
        }
      ]
    },
    {
      "name": "t000004001",
      "lineContainers": [
        {
          "name": "name",
          "line": "司波　達也"
        },
        {
          "name": "txt",
          "lines": [
            "なっ？\r\n",
            "エリカ待て！"
          ]
        },
        {
          "name": "voice",
          "line": "voe00000400100"
        }
      ]
    },
    {
      "name": "t000004002",
      "lineContainers": [
        {
          "name": "name",
          "line": "西城　レオンハルト"
        },
        {
          "name": "txt",
          "lines": [
            "……！？\r\n",
            "待て！\r\n",
            "エリカ！"
          ]
        },
        {
          "name": "voice",
          "line": "voe00000400200"
        }
      ]
    },
    {
      "name": "t000004003",
      "lineContainers": [
        {
          "name": "name",
          "line": "吉田　幹比古"
        },
        {
          "name": "txt",
          "lines": [
            "エリカ！\r\n",
            "待って！"
          ]
        },
        {
          "name": "voice",
          "line": "voe00000400300"
        }
      ]
    },
    {
      "name": "t000004004",
      "lineContainers": [
        {
          "name": "name",
          "line": "一条　将輝"
        },
        {
          "name": "txt",
          "lines": [
            "待て！\r\n",
            "まだだ！"
          ]
        },
        {
          "name": "voice",
          "line": "voe00000400400"
        }
      ]
    },
    {
      "name": "t000004005",
      "lineContainers": [
        {
          "name": "name",
          "line": "服部刑部少丞範蔵"
        },
        {
          "name": "txt",
          "lines": [
            "あっ！？\r\n",
            "このタイミングで出て来られては……！"
          ]
        },
        {
          "name": "voice",
          "line": "voe00000400500"
        }
      ]
    },
    {
      "name": "t000004006",
      "lineContainers": [
        {
          "name": "name",
          "line": "五十里　啓"
        },
        {
          "name": "txt",
          "lines": [
            "あっ！\r\n",
            "エリカくん\r\n",
            "今出てきてしまったら……！"
          ]
        },
        {
          "name": "voice",
          "line": "voe00000400600"
        }
      ]
    },
    {
      "name": "t000004007",
      "lineContainers": [
        {
          "name": "name",
          "line": "吉祥寺　真紅郎"
        },
        {
          "name": "txt",
          "lines": [
            "待った！\r\n",
            "今出てきたら……！"
          ]
        },
        {
          "name": "voice",
          "line": "voe00000400700"
        }
      ]
    },
    {
      "name": "t000004008",
      "lineContainers": [
        {
          "name": "name",
          "line": "千葉　エリカ"
        },
        {
          "name": "voice",
          "line": "voe00000400800"
        }
      ]
    },
    {
      "name": "t000004009",
      "lineContainers": [
        {
          "name": "name",
          "line": "千葉　エリカ"
        },
        {
          "name": "voice",
          "line": "voe00000400900"
        }
      ]
    },
    {
      "name": "t000004010",
      "lineContainers": [
        {
          "name": "name",
          "line": "司波　達也"
        },
        {
          "name": "txt",
          "lines": [
            "（蹴ったエリカの方が\r\n",
            "　痛そうだったな\r\n",
            "　すまん……）"
          ]
        },
        {
          "name": "voice",
          "line": "voe00000401000"
        }
      ]
    },
    {
      "name": "t000004011",
      "lineContainers": [
        {
          "name": "name",
          "line": "西城　レオンハルト"
        },
        {
          "name": "txt",
          "lines": [
            "（蹴りの一発くらいで\r\n",
            "　気が晴れるなら\r\n",
            "　構わねぇんだがな……）"
          ]
        },
        {
          "name": "voice",
          "line": "voe00000401100"
        }
      ]
    },
    {
      "name": "t000004012",
      "lineContainers": [
        {
          "name": "name",
          "line": "吉田　幹比古"
        },
        {
          "name": "txt",
          "lines": [
            "……エリカも\r\n",
            "手加減しないんだからなぁ\r\n",
            "痛つつ……"
          ]
        },
        {
          "name": "voice",
          "line": "voe00000401200"
        }
      ]
    },
    {
      "name": "t000004013",
      "lineContainers": [
        {
          "name": "name",
          "line": "一条　将輝"
        },
        {
          "name": "txt",
          "lines": [
            "（……強烈な蹴りを\r\n",
            "　お見舞いされてしまった……）"
          ]
        },
        {
          "name": "voice",
          "line": "voe00000401300"
        }
      ]
    },
    {
      "name": "t000004014",
      "lineContainers": [
        {
          "name": "name",
          "line": "服部刑部少丞範蔵"
        },
        {
          "name": "txt",
          "lines": [
            "（……先輩相手でも\r\n",
            "　アイツは遠慮がないな……）"
          ]
        },
        {
          "name": "voice",
          "line": "voe00000401400"
        }
      ]
    },
    {
      "name": "t000004015",
      "lineContainers": [
        {
          "name": "name",
          "line": "五十里　啓"
        },
        {
          "name": "txt",
          "lines": [
            "痛つ……\r\n",
            "やり過ぎだよ\r\n",
            "エリカくん……"
          ]
        },
        {
          "name": "voice",
          "line": "voe00000401500"
        }
      ]
    },
    {
      "name": "t000004016",
      "lineContainers": [
        {
          "name": "name",
          "line": "吉祥寺　真紅郎"
        },
        {
          "name": "voice",
          "line": "voe00000401600"
        }
      ]
    },
    {
      "name": "t000005001",
      "lineContainers": [
        {
          "name": "name",
          "line": "司波　達也"
        },
        {
          "name": "voice",
          "line": "voe00000500100"
        }
      ]
    },
    {
      "name": "t000005002",
      "lineContainers": [
        {
          "name": "name",
          "line": "西城　レオンハルト"
        },
        {
          "name": "txt",
          "lines": [
            "まだだ！\r\n",
            "光井！"
          ]
        },
        {
          "name": "voice",
          "line": "voe00000500200"
        }
      ]
    },
    {
      "name": "t000005003",
      "lineContainers": [
        {
          "name": "name",
          "line": "吉田　幹比古"
        },
        {
          "name": "txt",
          "lines": [
            "光井さん\r\n",
            "ダメだ！"
          ]
        },
        {
          "name": "voice",
          "line": "voe00000500300"
        }
      ]
    },
    {
      "name": "t000005004",
      "lineContainers": [
        {
          "name": "name",
          "line": "一条　将輝"
        },
        {
          "name": "txt",
          "lines": [
            "なっ！？\r\n",
            "今出て来られては……！"
          ]
        },
        {
          "name": "voice",
          "line": "voe00000500400"
        }
      ]
    },
    {
      "name": "t000005005",
      "lineContainers": [
        {
          "name": "name",
          "line": "服部刑部少丞範蔵"
        },
        {
          "name": "txt",
          "lines": [
            "光井さん！\r\n",
            "まだだ！"
          ]
        },
        {
          "name": "voice",
          "line": "voe00000500500"
        }
      ]
    },
    {
      "name": "t000005006",
      "lineContainers": [
        {
          "name": "name",
          "line": "五十里　啓"
        },
        {
          "name": "txt",
          "lines": [
            "光井さん\r\n",
            "待って！"
          ]
        },
        {
          "name": "voice",
          "line": "voe00000500600"
        }
      ]
    },
    {
      "name": "t000005007",
      "lineContainers": [
        {
          "name": "name",
          "line": "吉祥寺　真紅郎"
        },
        {
          "name": "txt",
          "lines": [
            "ストップ！\r\n",
            "まだ終わってない！"
          ]
        },
        {
          "name": "voice",
          "line": "voe00000500700"
        }
      ]
    },
    {
      "name": "t000005008",
      "lineContainers": [
        {
          "name": "name",
          "line": "光井　ほのか"
        },
        {
          "name": "voice",
          "line": "voe00000500800"
        }
      ]
    },
    {
      "name": "t000005009",
      "lineContainers": [
        {
          "name": "name",
          "line": "光井　ほのか"
        },
        {
          "name": "voice",
          "line": "voe00000500900"
        }
      ]
    },
    {
      "name": "t000005010",
      "lineContainers": [
        {
          "name": "name",
          "line": "司波　達也"
        },
        {
          "name": "txt",
          "lines": [
            "（目が眩む\r\n",
            "　凄まじい速さの閃光魔法だったな……）"
          ]
        },
        {
          "name": "voice",
          "line": "voe00000501000"
        }
      ]
    },
    {
      "name": "t000005011",
      "lineContainers": [
        {
          "name": "name",
          "line": "西城　レオンハルト"
        },
        {
          "name": "txt",
          "lines": [
            "（さすが光井の閃光魔法\r\n",
            "　って　感心してる場合じゃねぇか……）"
          ]
        },
        {
          "name": "voice",
          "line": "voe00000501100"
        }
      ]
    },
    {
      "name": "t000005012",
      "lineContainers": [
        {
          "name": "name",
          "line": "吉田　幹比古"
        },
        {
          "name": "voice",
          "line": "voe00000501200"
        }
      ]
    },
    {
      "name": "t000005013",
      "lineContainers": [
        {
          "name": "name",
          "line": "一条　将輝"
        },
        {
          "name": "txt",
          "lines": [
            "（今のは閃光魔法か\r\n",
            "　それにしても\r\n",
            "　恐ろしい展開速度だったな……）"
          ]
        },
        {
          "name": "voice",
          "line": "voe00000501300"
        }
      ]
    },
    {
      "name": "t000005014",
      "lineContainers": [
        {
          "name": "name",
          "line": "服部刑部少丞範蔵"
        },
        {
          "name": "txt",
          "lines": [
            "ぐっ……\r\n",
            "強力な閃光魔法だな……"
          ]
        },
        {
          "name": "voice",
          "line": "voe00000501400"
        }
      ]
    },
    {
      "name": "t000005015",
      "lineContainers": [
        {
          "name": "name",
          "line": "五十里　啓"
        },
        {
          "name": "txt",
          "lines": [
            "う～ん\r\n",
            "目が眩む……"
          ]
        },
        {
          "name": "voice",
          "line": "voe00000501500"
        }
      ]
    },
    {
      "name": "t000005016",
      "lineContainers": [
        {
          "name": "name",
          "line": "吉祥寺　真紅郎"
        },
        {
          "name": "txt",
          "lines": [
            "うっ\r\n",
            "視界が……"
          ]
        },
        {
          "name": "voice",
          "line": "voe00000501600"
        }
      ]
    },
    {
      "name": "t000006001",
      "lineContainers": [
        {
          "name": "name",
          "line": "司波　達也"
        },
        {
          "name": "txt",
          "lines": [
            "えっ？\r\n",
            "雫！？"
          ]
        },
        {
          "name": "voice",
          "line": "voe00000600100"
        }
      ]
    },
    {
      "name": "t000006002",
      "lineContainers": [
        {
          "name": "name",
          "line": "西城　レオンハルト"
        },
        {
          "name": "txt",
          "lines": [
            "チョッ\n",
            "チョッと待った……！"
          ]
        },
        {
          "name": "voice",
          "line": "voe00000600200"
        }
      ]
    },
    {
      "name": "t000006003",
      "lineContainers": [
        {
          "name": "name",
          "line": "吉田　幹比古"
        },
        {
          "name": "txt",
          "lines": [
            "えっ？\r\n",
            "どうして……！？"
          ]
        },
        {
          "name": "voice",
          "line": "voe00000600300"
        }
      ]
    },
    {
      "name": "t000006004",
      "lineContainers": [
        {
          "name": "name",
          "line": "一条　将輝"
        },
        {
          "name": "txt",
          "lines": [
            "あっ！？\r\n",
            "何故！？"
          ]
        },
        {
          "name": "voice",
          "line": "voe00000600400"
        }
      ]
    },
    {
      "name": "t000006005",
      "lineContainers": [
        {
          "name": "name",
          "line": "服部刑部少丞範蔵"
        },
        {
          "name": "txt",
          "lines": [
            "なっ！？\r\n",
            "まだ早い……！"
          ]
        },
        {
          "name": "voice",
          "line": "voe00000600500"
        }
      ]
    },
    {
      "name": "t000006006",
      "lineContainers": [
        {
          "name": "name",
          "line": "五十里　啓"
        },
        {
          "name": "txt",
          "lines": [
            "えっ？\r\n",
            "今出てきたら……！"
          ]
        },
        {
          "name": "voice",
          "line": "voe00000600600"
        }
      ]
    },
    {
      "name": "t000006007",
      "lineContainers": [
        {
          "name": "name",
          "line": "吉祥寺　真紅郎"
        },
        {
          "name": "txt",
          "lines": [
            "あっ！？\r\n",
            "まだ……！"
          ]
        },
        {
          "name": "voice",
          "line": "voe00000600700"
        }
      ]
    },
    {
      "name": "t000006008",
      "lineContainers": [
        {
          "name": "name",
          "line": "北山　雫"
        },
        {
          "name": "txt",
          "lines": [
            "あれっ？\r\n",
            "間違えた"
          ]
        },
        {
          "name": "voice",
          "line": "voe00000600800"
        }
      ]
    },
    {
      "name": "t000006009",
      "lineContainers": [
        {
          "name": "name",
          "line": "北山　雫"
        },
        {
          "name": "voice",
          "line": "voe00000600900"
        }
      ]
    },
    {
      "name": "t000006010",
      "lineContainers": [
        {
          "name": "name",
          "line": "司波　達也"
        },
        {
          "name": "txt",
          "lines": [
            "（一瞬で視界を塞がれた……\r\n",
            "　さすが雫）"
          ]
        },
        {
          "name": "voice",
          "line": "voe00000601000"
        }
      ]
    },
    {
      "name": "t000006011",
      "lineContainers": [
        {
          "name": "name",
          "line": "西城　レオンハルト"
        },
        {
          "name": "txt",
          "lines": [
            "んっ？\r\n",
            "どうしたんだ？\r\n",
            "何も見えねぇ……"
          ]
        },
        {
          "name": "voice",
          "line": "voe00000601100"
        }
      ]
    },
    {
      "name": "t000006012",
      "lineContainers": [
        {
          "name": "name",
          "line": "吉田　幹比古"
        },
        {
          "name": "txt",
          "lines": [
            "（……こんな時でも\r\n",
            "　慌てず冷静に対処するとは……\r\n",
            "　さすが　と言っていいのかどうか……）"
          ]
        },
        {
          "name": "voice",
          "line": "voe00000601200"
        }
      ]
    },
    {
      "name": "t000006013",
      "lineContainers": [
        {
          "name": "name",
          "line": "一条　将輝"
        },
        {
          "name": "voice",
          "line": "voe00000601300"
        }
      ]
    },
    {
      "name": "t000006014",
      "lineContainers": [
        {
          "name": "name",
          "line": "服部刑部少丞範蔵"
        },
        {
          "name": "txt",
          "lines": [
            "（視界を一瞬で塞いだのか\r\n",
            "　冷静な判断力だな……）"
          ]
        },
        {
          "name": "voice",
          "line": "voe00000601400"
        }
      ]
    },
    {
      "name": "t000006015",
      "lineContainers": [
        {
          "name": "name",
          "line": "五十里　啓"
        },
        {
          "name": "txt",
          "lines": [
            "ん？\r\n",
            "……もしかして\r\n",
            "視界を塞がれてしまったのか……"
          ]
        },
        {
          "name": "voice",
          "line": "voe00000601500"
        }
      ]
    },
    {
      "name": "t000006016",
      "lineContainers": [
        {
          "name": "name",
          "line": "吉祥寺　真紅郎"
        },
        {
          "name": "txt",
          "lines": [
            "あれっ？\r\n",
            "何も見えない……"
          ]
        },
        {
          "name": "voice",
          "line": "voe00000601600"
        }
      ]
    },
    {
      "name": "t000007001",
      "lineContainers": [
        {
          "name": "name",
          "line": "司波　達也"
        },
        {
          "name": "txt",
          "lines": [
            "会長！\n",
            "まだです！"
          ]
        },
        {
          "name": "voice",
          "line": "voe00000700100"
        }
      ]
    },
    {
      "name": "t000007002",
      "lineContainers": [
        {
          "name": "name",
          "line": "西城　レオンハルト"
        },
        {
          "name": "txt",
          "lines": [
            "あ！？\r\n",
            "会長！？"
          ]
        },
        {
          "name": "voice",
          "line": "voe00000700200"
        }
      ]
    },
    {
      "name": "t000007003",
      "lineContainers": [
        {
          "name": "name",
          "line": "吉田　幹比古"
        },
        {
          "name": "txt",
          "lines": [
            "あっ！？\r\n",
            "会長！"
          ]
        },
        {
          "name": "voice",
          "line": "voe00000700300"
        }
      ]
    },
    {
      "name": "t000007004",
      "lineContainers": [
        {
          "name": "name",
          "line": "一条　将輝"
        },
        {
          "name": "txt",
          "lines": [
            "……！？\r\n",
            "ま　まだです！"
          ]
        },
        {
          "name": "voice",
          "line": "voe00000700400"
        }
      ]
    },
    {
      "name": "t000007005",
      "lineContainers": [
        {
          "name": "name",
          "line": "服部刑部少丞範蔵"
        },
        {
          "name": "txt",
          "lines": [
            "会長！\n",
            "お待ちください！"
          ]
        },
        {
          "name": "voice",
          "line": "voe00000700500"
        }
      ]
    },
    {
      "name": "t000007006",
      "lineContainers": [
        {
          "name": "name",
          "line": "五十里　啓"
        },
        {
          "name": "txt",
          "lines": [
            "お待ちください！\r\n",
            "まだ……！"
          ]
        },
        {
          "name": "voice",
          "line": "voe00000700600"
        }
      ]
    },
    {
      "name": "t000007007",
      "lineContainers": [
        {
          "name": "name",
          "line": "吉祥寺　真紅郎"
        },
        {
          "name": "txt",
          "lines": [
            "待ってください！\r\n",
            "まだです！"
          ]
        },
        {
          "name": "voice",
          "line": "voe00000700700"
        }
      ]
    },
    {
      "name": "t000007008",
      "lineContainers": [
        {
          "name": "name",
          "line": "七草　真由美"
        },
        {
          "name": "voice",
          "line": "voe00000700800"
        }
      ]
    },
    {
      "name": "t000007009",
      "lineContainers": [
        {
          "name": "name",
          "line": "七草　真由美"
        },
        {
          "name": "voice",
          "line": "voe00000700900"
        }
      ]
    },
    {
      "name": "t000007010",
      "lineContainers": [
        {
          "name": "name",
          "line": "七草　真由美"
        },
        {
          "name": "txt",
          "lines": [
            "こっこれは\r\n",
            "貸しにしておくわね"
          ]
        },
        {
          "name": "voice",
          "line": "voe00000701000"
        }
      ]
    },
    {
      "name": "t000007011",
      "lineContainers": [
        {
          "name": "name",
          "line": "司波　達也"
        },
        {
          "name": "txt",
          "lines": [
            "（この貸しは\r\n",
            "　そう簡単に返せそうにないな……）"
          ]
        },
        {
          "name": "voice",
          "line": "voe00000701100"
        }
      ]
    },
    {
      "name": "t000007012",
      "lineContainers": [
        {
          "name": "name",
          "line": "西城　レオンハルト"
        },
        {
          "name": "txt",
          "lines": [
            "（……デケェ貸しを\r\n",
            "　作られちまったもんだな）"
          ]
        },
        {
          "name": "voice",
          "line": "voe00000701200"
        }
      ]
    },
    {
      "name": "t000007013",
      "lineContainers": [
        {
          "name": "name",
          "line": "吉田　幹比古"
        },
        {
          "name": "txt",
          "lines": [
            "（しまった……\r\n",
            "　この貸しは大きくなりそうだ……）"
          ]
        },
        {
          "name": "voice",
          "line": "voe00000701300"
        }
      ]
    },
    {
      "name": "t000007014",
      "lineContainers": [
        {
          "name": "name",
          "line": "一条　将輝"
        },
        {
          "name": "txt",
          "lines": [
            "（返せるものなら返したいものだが……\r\n",
            "　果たしていつになるかな……）"
          ]
        },
        {
          "name": "voice",
          "line": "voe00000701400"
        }
      ]
    },
    {
      "name": "t000007015",
      "lineContainers": [
        {
          "name": "name",
          "line": "服部刑部少丞範蔵"
        },
        {
          "name": "txt",
          "lines": [
            "（……会長には\n",
            "　これまで以上に\n",
            "　頭が上がらなくなりそうだな……）"
          ]
        },
        {
          "name": "voice",
          "line": "voe00000701500"
        }
      ]
    },
    {
      "name": "t000007016",
      "lineContainers": [
        {
          "name": "name",
          "line": "五十里　啓"
        },
        {
          "name": "txt",
          "lines": [
            "僕にできる範囲であれば\r\n",
            "いつでも構いませんよ"
          ]
        },
        {
          "name": "voice",
          "line": "voe00000701600"
        }
      ]
    },
    {
      "name": "t000007017",
      "lineContainers": [
        {
          "name": "name",
          "line": "吉祥寺　真紅郎"
        },
        {
          "name": "txt",
          "lines": [
            "（う～ん……\r\n",
            "　マズイことになってしまったな……）"
          ]
        },
        {
          "name": "voice",
          "line": "voe00000701700"
        }
      ]
    },
    {
      "name": "t000008001",
      "lineContainers": [
        {
          "name": "name",
          "line": "司波　達也"
        },
        {
          "name": "txt",
          "lines": [
            "あっまだっ！\r\n",
            "渡辺先輩！"
          ]
        },
        {
          "name": "voice",
          "line": "voe00000800100"
        }
      ]
    },
    {
      "name": "t000008002",
      "lineContainers": [
        {
          "name": "name",
          "line": "西城　レオンハルト"
        },
        {
          "name": "txt",
          "lines": [
            "まだです！\r\n",
            "まだ終わってませんって！"
          ]
        },
        {
          "name": "voice",
          "line": "voe00000800200"
        }
      ]
    },
    {
      "name": "t000008003",
      "lineContainers": [
        {
          "name": "name",
          "line": "吉田　幹比古"
        },
        {
          "name": "txt",
          "lines": [
            "まだです！\r\n",
            "渡辺先輩！"
          ]
        },
        {
          "name": "voice",
          "line": "voe00000800300"
        }
      ]
    },
    {
      "name": "t000008004",
      "lineContainers": [
        {
          "name": "name",
          "line": "一条　将輝"
        },
        {
          "name": "txt",
          "lines": [
            "まだです！\r\n",
            "お待ちください！"
          ]
        },
        {
          "name": "voice",
          "line": "voe00000800400"
        }
      ]
    },
    {
      "name": "t000008005",
      "lineContainers": [
        {
          "name": "name",
          "line": "服部刑部少丞範蔵"
        },
        {
          "name": "txt",
          "lines": [
            "渡辺先輩！？\r\n",
            "まだです！"
          ]
        },
        {
          "name": "voice",
          "line": "voe00000800500"
        }
      ]
    },
    {
      "name": "t000008006",
      "lineContainers": [
        {
          "name": "name",
          "line": "五十里　啓"
        },
        {
          "name": "txt",
          "lines": [
            "えっ？\r\n",
            "渡辺先輩！？"
          ]
        },
        {
          "name": "voice",
          "line": "voe00000800600"
        }
      ]
    },
    {
      "name": "t000008007",
      "lineContainers": [
        {
          "name": "name",
          "line": "吉祥寺　真紅郎"
        },
        {
          "name": "txt",
          "lines": [
            "ダメです！\r\n",
            "まだ終わって……！"
          ]
        },
        {
          "name": "voice",
          "line": "voe00000800700"
        }
      ]
    },
    {
      "name": "t000008008",
      "lineContainers": [
        {
          "name": "name",
          "line": "渡辺　摩利"
        },
        {
          "name": "txt",
          "lines": [
            "おやっ！？\r\n",
            "どういうことだ？"
          ]
        },
        {
          "name": "voice",
          "line": "voe00000800800"
        }
      ]
    },
    {
      "name": "t000008009",
      "lineContainers": [
        {
          "name": "name",
          "line": "渡辺　摩利"
        },
        {
          "name": "txt",
          "lines": [
            "覗きとは\r\n",
            "いい度胸じゃないか！？"
          ]
        },
        {
          "name": "voice",
          "line": "voe00000800900"
        }
      ]
    },
    {
      "name": "t000008010",
      "lineContainers": [
        {
          "name": "name",
          "line": "司波　達也"
        },
        {
          "name": "txt",
          "lines": [
            "（腰の入った\r\n",
            "　いいパンチだった\r\n",
            "　殴った手の方が痛そうだったが……）"
          ]
        },
        {
          "name": "voice",
          "line": "voe00000801000"
        }
      ]
    },
    {
      "name": "t000008011",
      "lineContainers": [
        {
          "name": "name",
          "line": "西城　レオンハルト"
        },
        {
          "name": "txt",
          "lines": [
            "（……こっちの身体よりも\r\n",
            "　殴った手の方にデカいダメージが\r\n",
            "　あったみてぇだな）"
          ]
        },
        {
          "name": "voice",
          "line": "voe00000801100"
        }
      ]
    },
    {
      "name": "t000008012",
      "lineContainers": [
        {
          "name": "name",
          "line": "吉田　幹比古"
        },
        {
          "name": "txt",
          "lines": [
            "（うぐっ　強烈なパンチだ\r\n",
            "　……やっぱり　僕は鍛え方が\r\n",
            "　足りないのかもしれないな……）"
          ]
        },
        {
          "name": "voice",
          "line": "voe00000801200"
        }
      ]
    },
    {
      "name": "t000008013",
      "lineContainers": [
        {
          "name": "name",
          "line": "一条　将輝"
        },
        {
          "name": "voice",
          "line": "voe00000801300"
        }
      ]
    },
    {
      "name": "t000008014",
      "lineContainers": [
        {
          "name": "name",
          "line": "服部刑部少丞範蔵"
        },
        {
          "name": "txt",
          "lines": [
            "（鉄拳制裁とは……\r\n",
            "　実に渡辺先輩らしいな）"
          ]
        },
        {
          "name": "voice",
          "line": "voe00000801400"
        }
      ]
    },
    {
      "name": "t000008015",
      "lineContainers": [
        {
          "name": "name",
          "line": "五十里　啓"
        },
        {
          "name": "txt",
          "lines": [
            "な　何だか\r\n",
            "身体がフラフラしてきた……"
          ]
        },
        {
          "name": "voice",
          "line": "voe00000801500"
        }
      ]
    },
    {
      "name": "t000008016",
      "lineContainers": [
        {
          "name": "name",
          "line": "吉祥寺　真紅郎"
        },
        {
          "name": "voice",
          "line": "voe00000401600"
        }
      ]
    },
    {
      "name": "t000009001",
      "lineContainers": [
        {
          "name": "name",
          "line": "司波　達也"
        },
        {
          "name": "txt",
          "lines": [
            "エイミィ！？\r\n",
            "まだだ！"
          ]
        },
        {
          "name": "voice",
          "line": "voe00000900100"
        }
      ]
    },
    {
      "name": "t000009002",
      "lineContainers": [
        {
          "name": "name",
          "line": "西城　レオンハルト"
        },
        {
          "name": "txt",
          "lines": [
            "お　おい……\r\n",
            "今出て来られたら……"
          ]
        },
        {
          "name": "voice",
          "line": "voe00000900200"
        }
      ]
    },
    {
      "name": "t000009003",
      "lineContainers": [
        {
          "name": "name",
          "line": "吉田　幹比古"
        },
        {
          "name": "txt",
          "lines": [
            "えっ\r\n",
            "まだ……"
          ]
        },
        {
          "name": "voice",
          "line": "voe00000900300"
        }
      ]
    },
    {
      "name": "t000009004",
      "lineContainers": [
        {
          "name": "name",
          "line": "一条　将輝"
        },
        {
          "name": "txt",
          "lines": [
            "あっ！？\r\n",
            "何故！？"
          ]
        },
        {
          "name": "voice",
          "line": "voe00000600400"
        }
      ]
    },
    {
      "name": "t000009005",
      "lineContainers": [
        {
          "name": "name",
          "line": "服部刑部少丞範蔵"
        },
        {
          "name": "voice",
          "line": "voe00000900500"
        }
      ]
    },
    {
      "name": "t000009006",
      "lineContainers": [
        {
          "name": "name",
          "line": "五十里　啓"
        },
        {
          "name": "txt",
          "lines": [
            "あっ\r\n",
            "まだ……"
          ]
        },
        {
          "name": "voice",
          "line": "voe00000900600"
        }
      ]
    },
    {
      "name": "t000009007",
      "lineContainers": [
        {
          "name": "name",
          "line": "吉祥寺　真紅郎"
        },
        {
          "name": "txt",
          "lines": [
            "えっ\r\n",
            "まだ終わってな……！"
          ]
        },
        {
          "name": "voice",
          "line": "voe00000300600"
        }
      ]
    },
    {
      "name": "t000009008",
      "lineContainers": [
        {
          "name": "name",
          "line": "明智　英美"
        },
        {
          "name": "voice",
          "line": "voe00000900800"
        }
      ]
    },
    {
      "name": "t000009009",
      "lineContainers": [
        {
          "name": "name",
          "line": "明智　英美"
        },
        {
          "name": "txt",
          "lines": [
            "何で\n",
            "いるのっ！？"
          ]
        },
        {
          "name": "voice",
          "line": "voe00000900900"
        }
      ]
    },
    {
      "name": "t000009010",
      "lineContainers": [
        {
          "name": "name",
          "line": "司波　達也"
        },
        {
          "name": "txt",
          "lines": [
            "（ワープしたかと思う程の速さで\r\n",
            "　目の前からいなくなった……）"
          ]
        },
        {
          "name": "voice",
          "line": "voe00000901000"
        }
      ]
    },
    {
      "name": "t000009011",
      "lineContainers": [
        {
          "name": "name",
          "line": "西城　レオンハルト"
        },
        {
          "name": "txt",
          "lines": [
            "……言い訳もできねぇ内に\r\n",
            "いなくなっちまった"
          ]
        },
        {
          "name": "voice",
          "line": "voe00000901100"
        }
      ]
    },
    {
      "name": "t000009012",
      "lineContainers": [
        {
          "name": "name",
          "line": "吉田　幹比古"
        },
        {
          "name": "txt",
          "lines": [
            "……あの姿のままどこかへ消えてしまうのは\r\n",
            "それはそれでマズイと思うんだけど……"
          ]
        },
        {
          "name": "voice",
          "line": "voe00000901200"
        }
      ]
    },
    {
      "name": "t000009013",
      "lineContainers": [
        {
          "name": "name",
          "line": "一条　将輝"
        },
        {
          "name": "txt",
          "lines": [
            "（瞬く間に\r\n",
            "　いなくなってしまった……）"
          ]
        },
        {
          "name": "voice",
          "line": "voe00000901300"
        }
      ]
    },
    {
      "name": "t000009014",
      "lineContainers": [
        {
          "name": "name",
          "line": "服部刑部少丞範蔵"
        },
        {
          "name": "txt",
          "lines": [
            "……早いな\r\n",
            "一瞬の内にいなくなってしまった"
          ]
        },
        {
          "name": "voice",
          "line": "voe00000901400"
        }
      ]
    },
    {
      "name": "t000009015",
      "lineContainers": [
        {
          "name": "name",
          "line": "五十里　啓"
        },
        {
          "name": "txt",
          "lines": [
            "うん？\r\n",
            "消えた？"
          ]
        },
        {
          "name": "voice",
          "line": "voe00000901500"
        }
      ]
    },
    {
      "name": "t000009016",
      "lineContainers": [
        {
          "name": "name",
          "line": "吉祥寺　真紅郎"
        },
        {
          "name": "txt",
          "lines": [
            "あれ……？\r\n",
            "もういない……"
          ]
        },
        {
          "name": "voice",
          "line": "voe00000901600"
        }
      ]
    },
    {
      "name": "t000010001",
      "lineContainers": [
        {
          "name": "name",
          "line": "司波　達也"
        },
        {
          "name": "txt",
          "lines": [
            "あっ！？\r\n",
            "千代田先輩！"
          ]
        },
        {
          "name": "voice",
          "line": "voe00001000100"
        }
      ]
    },
    {
      "name": "t000010002",
      "lineContainers": [
        {
          "name": "name",
          "line": "西城　レオンハルト"
        },
        {
          "name": "txt",
          "lines": [
            "……！？\r\n",
            "待ってください！"
          ]
        },
        {
          "name": "voice",
          "line": "voe00001000200"
        }
      ]
    },
    {
      "name": "t000010003",
      "lineContainers": [
        {
          "name": "name",
          "line": "吉田　幹比古"
        },
        {
          "name": "voice",
          "line": "voe00001000300"
        }
      ]
    },
    {
      "name": "t000010004",
      "lineContainers": [
        {
          "name": "name",
          "line": "一条　将輝"
        },
        {
          "name": "txt",
          "lines": [
            "……！？\r\n",
            "ま　まだです！"
          ]
        },
        {
          "name": "voice",
          "line": "voe00000700400"
        }
      ]
    },
    {
      "name": "t000010005",
      "lineContainers": [
        {
          "name": "name",
          "line": "服部刑部少丞範蔵"
        },
        {
          "name": "txt",
          "lines": [
            "……！？\r\n",
            "まだだ！\r\n",
            "まだ終わってない！"
          ]
        },
        {
          "name": "voice",
          "line": "voe00001000500"
        }
      ]
    },
    {
      "name": "t000010006",
      "lineContainers": [
        {
          "name": "name",
          "line": "五十里　啓"
        },
        {
          "name": "voice",
          "line": "voe00001000600"
        }
      ]
    },
    {
      "name": "t000010007",
      "lineContainers": [
        {
          "name": "name",
          "line": "吉祥寺　真紅郎"
        },
        {
          "name": "txt",
          "lines": [
            "待ってください！\r\n",
            "まだです！"
          ]
        },
        {
          "name": "voice",
          "line": "voe00000700700"
        }
      ]
    },
    {
      "name": "t000010008",
      "lineContainers": [
        {
          "name": "name",
          "line": "千代田　花音"
        },
        {
          "name": "voice",
          "line": "voe00001000800"
        }
      ]
    },
    {
      "name": "t000010009",
      "lineContainers": [
        {
          "name": "name",
          "line": "千代田　花音"
        },
        {
          "name": "txt",
          "lines": [
            "なに\r\n",
            "見てんの……"
          ]
        },
        {
          "name": "voice",
          "line": "voe00001000900"
        }
      ]
    },
    {
      "name": "t000010010",
      "lineContainers": [
        {
          "name": "name",
          "line": "千代田　花音"
        },
        {
          "name": "voice",
          "line": "voe00001001000"
        }
      ]
    },
    {
      "name": "t000010011",
      "lineContainers": [
        {
          "name": "name",
          "line": "司波　達也"
        },
        {
          "name": "txt",
          "lines": [
            "（ゴホッゴホッ……\n",
            "　危うく爆発に巻き込まれるところだった）"
          ]
        },
        {
          "name": "voice",
          "line": "voe00001001100"
        }
      ]
    },
    {
      "name": "t000010012",
      "lineContainers": [
        {
          "name": "name",
          "line": "西城　レオンハルト"
        },
        {
          "name": "txt",
          "lines": [
            "（……ヤバかった\r\n",
            "　もう少しで\r\n",
            "　モロに直撃を食らうトコだったぜ）"
          ]
        },
        {
          "name": "voice",
          "line": "voe00001001200"
        }
      ]
    },
    {
      "name": "t000010013",
      "lineContainers": [
        {
          "name": "name",
          "line": "吉田　幹比古"
        },
        {
          "name": "txt",
          "lines": [
            "（お　恐ろしい……\n",
            "　危うく爆発に巻き込まれるところだった）"
          ]
        },
        {
          "name": "voice",
          "line": "voe00001001300"
        }
      ]
    },
    {
      "name": "t000010014",
      "lineContainers": [
        {
          "name": "name",
          "line": "一条　将輝"
        },
        {
          "name": "voice",
          "line": "voe00001001400"
        }
      ]
    },
    {
      "name": "t000010015",
      "lineContainers": [
        {
          "name": "name",
          "line": "服部刑部少丞範蔵"
        },
        {
          "name": "txt",
          "lines": [
            "……まったく\r\n",
            "高火力の魔法を使用するのは\r\n",
            "精密機器の側では控えるようにしておけ"
          ]
        },
        {
          "name": "voice",
          "line": "voe00001001500"
        }
      ]
    },
    {
      "name": "t000010016",
      "lineContainers": [
        {
          "name": "name",
          "line": "五十里　啓"
        },
        {
          "name": "voice",
          "line": "voe00001001600"
        }
      ]
    },
    {
      "name": "t000010017",
      "lineContainers": [
        {
          "name": "name",
          "line": "吉祥寺　真紅郎"
        },
        {
          "name": "voice",
          "line": "voe00001001700"
        }
      ]
    },
    {
      "name": "t000011001",
      "lineContainers": [
        {
          "name": "name",
          "line": "司波　達也"
        },
        {
          "name": "voice",
          "line": "voe00001100100"
        }
      ]
    },
    {
      "name": "t000011002",
      "lineContainers": [
        {
          "name": "name",
          "line": "西城　レオンハルト"
        },
        {
          "name": "voice",
          "line": "voe00001100200"
        }
      ]
    },
    {
      "name": "t000011003",
      "lineContainers": [
        {
          "name": "name",
          "line": "吉田　幹比古"
        },
        {
          "name": "txt",
          "lines": [
            "えっ！？\r\n",
            "ピクシー！"
          ]
        },
        {
          "name": "voice",
          "line": "voe00001100300"
        }
      ]
    },
    {
      "name": "t000011004",
      "lineContainers": [
        {
          "name": "name",
          "line": "一条　将輝"
        },
        {
          "name": "txt",
          "lines": [
            "待て！\r\n",
            "まだだ！"
          ]
        },
        {
          "name": "voice",
          "line": "voe00000400400"
        }
      ]
    },
    {
      "name": "t000011005",
      "lineContainers": [
        {
          "name": "name",
          "line": "服部刑部少丞範蔵"
        },
        {
          "name": "voice",
          "line": "voe00001100500"
        }
      ]
    },
    {
      "name": "t000011006",
      "lineContainers": [
        {
          "name": "name",
          "line": "五十里　啓"
        },
        {
          "name": "txt",
          "lines": [
            "あっ\r\n",
            "まだ……"
          ]
        },
        {
          "name": "voice",
          "line": "voe00000900600"
        }
      ]
    },
    {
      "name": "t000011007",
      "lineContainers": [
        {
          "name": "name",
          "line": "吉祥寺　真紅郎"
        },
        {
          "name": "txt",
          "lines": [
            "あっ！？\r\n",
            "まだ……！"
          ]
        },
        {
          "name": "voice",
          "line": "voe00000600700"
        }
      ]
    },
    {
      "name": "t000011008",
      "lineContainers": [
        {
          "name": "name",
          "line": "ピクシー"
        },
        {
          "name": "voice",
          "line": "voe00001100800"
        }
      ]
    },
    {
      "name": "t000011009",
      "lineContainers": [
        {
          "name": "name",
          "line": "ピクシー"
        },
        {
          "name": "voice",
          "line": "voe00001100900"
        }
      ]
    },
    {
      "name": "t000011010",
      "lineContainers": [
        {
          "name": "name",
          "line": "司波　達也"
        },
        {
          "name": "txt",
          "lines": [
            "ピクシー\r\n",
            "早く服を着るんだ"
          ]
        },
        {
          "name": "voice",
          "line": "voe00001101000"
        }
      ]
    },
    {
      "name": "t000011011",
      "lineContainers": [
        {
          "name": "name",
          "line": "西城　レオンハルト"
        },
        {
          "name": "txt",
          "lines": [
            "わ　悪い！\r\n",
            "すぐ出てくから\r\n",
            "その間に着替えててくれ！"
          ]
        },
        {
          "name": "voice",
          "line": "voe00001101100"
        }
      ]
    },
    {
      "name": "t000011012",
      "lineContainers": [
        {
          "name": "name",
          "line": "吉田　幹比古"
        },
        {
          "name": "txt",
          "lines": [
            "い　いいから\r\n",
            "早く服を着て！"
          ]
        },
        {
          "name": "voice",
          "line": "voe00001101200"
        }
      ]
    },
    {
      "name": "t000011013",
      "lineContainers": [
        {
          "name": "name",
          "line": "一条　将輝"
        },
        {
          "name": "txt",
          "lines": [
            "ふっ　服を……\r\n",
            "早く着替えてくれ！"
          ]
        },
        {
          "name": "voice",
          "line": "voe00001101300"
        }
      ]
    },
    {
      "name": "t000011014",
      "lineContainers": [
        {
          "name": "name",
          "line": "服部刑部少丞範蔵"
        },
        {
          "name": "txt",
          "lines": [
            "……すまない\r\n",
            "出ていくから\r\n",
            "その間に着替えを済ませてくれ"
          ]
        },
        {
          "name": "voice",
          "line": "voe00001101400"
        }
      ]
    },
    {
      "name": "t000011015",
      "lineContainers": [
        {
          "name": "name",
          "line": "五十里　啓"
        },
        {
          "name": "txt",
          "lines": [
            "あっ　ゴメン\r\n",
            "出ていくから\r\n",
            "その間に服を……"
          ]
        },
        {
          "name": "voice",
          "line": "voe00001101500"
        }
      ]
    },
    {
      "name": "t000011016",
      "lineContainers": [
        {
          "name": "name",
          "line": "吉祥寺　真紅郎"
        },
        {
          "name": "txt",
          "lines": [
            "えーっと……\r\n",
            "その　服を……"
          ]
        },
        {
          "name": "voice",
          "line": "voe00001101600"
        }
      ]
    },
    {
      "name": "t000012001",
      "lineContainers": [
        {
          "name": "name",
          "line": "司波　達也"
        },
        {
          "name": "txt",
          "lines": [
            "！？\r\n",
            "待てっ！\r\n",
            "リーナ！"
          ]
        },
        {
          "name": "voice",
          "line": "voe00001200100"
        }
      ]
    },
    {
      "name": "t000012002",
      "lineContainers": [
        {
          "name": "name",
          "line": "西城　レオンハルト"
        },
        {
          "name": "txt",
          "lines": [
            "待て！\r\n",
            "止まれ！"
          ]
        },
        {
          "name": "voice",
          "line": "voe00001200200"
        }
      ]
    },
    {
      "name": "t000012003",
      "lineContainers": [
        {
          "name": "name",
          "line": "吉田　幹比古"
        },
        {
          "name": "txt",
          "lines": [
            "……！？\r\n",
            "リーナ！\r\n",
            "ストップ！"
          ]
        },
        {
          "name": "voice",
          "line": "voe00001200300"
        }
      ]
    },
    {
      "name": "t000012004",
      "lineContainers": [
        {
          "name": "name",
          "line": "一条　将輝"
        },
        {
          "name": "txt",
          "lines": [
            "なっ！？\r\n",
            "今出て来られては……！"
          ]
        },
        {
          "name": "voice",
          "line": "voe00000500400"
        }
      ]
    },
    {
      "name": "t000012005",
      "lineContainers": [
        {
          "name": "name",
          "line": "服部刑部少丞範蔵"
        },
        {
          "name": "voice",
          "line": "voe00000900500"
        }
      ]
    },
    {
      "name": "t000012006",
      "lineContainers": [
        {
          "name": "name",
          "line": "五十里　啓"
        },
        {
          "name": "txt",
          "lines": [
            "えっ？\r\n",
            "今出てきたら……！"
          ]
        },
        {
          "name": "voice",
          "line": "voe00000600600"
        }
      ]
    },
    {
      "name": "t000012007",
      "lineContainers": [
        {
          "name": "name",
          "line": "吉祥寺　真紅郎"
        },
        {
          "name": "txt",
          "lines": [
            "待った！\r\n",
            "今出てきたら……！"
          ]
        },
        {
          "name": "voice",
          "line": "voe00000400700"
        }
      ]
    },
    {
      "name": "t000012008",
      "lineContainers": [
        {
          "name": "name",
          "line": "アンジェリーナ・クドウ・シールズ"
        },
        {
          "name": "voice",
          "line": "voe00001200800"
        }
      ]
    },
    {
      "name": "t000012009",
      "lineContainers": [
        {
          "name": "name",
          "line": "アンジェリーナ・クドウ・シールズ"
        },
        {
          "name": "voice",
          "line": "voe00001200900"
        }
      ]
    },
    {
      "name": "t000012010",
      "lineContainers": [
        {
          "name": "name",
          "line": "司波　達也"
        },
        {
          "name": "txt",
          "lines": [
            "（逃げずに受けたせいか\r\n",
            "　さすがに頬がヒリヒリする……）"
          ]
        },
        {
          "name": "voice",
          "line": "voe00001201000"
        }
      ]
    },
    {
      "name": "t000012011",
      "lineContainers": [
        {
          "name": "name",
          "line": "西城　レオンハルト"
        },
        {
          "name": "txt",
          "lines": [
            "（……ビンタ一発で\r\n",
            "　気が済むのかな）"
          ]
        },
        {
          "name": "voice",
          "line": "voe00001201100"
        }
      ]
    },
    {
      "name": "t000012012",
      "lineContainers": [
        {
          "name": "name",
          "line": "吉田　幹比古"
        },
        {
          "name": "txt",
          "lines": [
            "うっ\r\n",
            "リーナ……\r\n",
            "もう少し手加減してくれ……"
          ]
        },
        {
          "name": "voice",
          "line": "voe00001201200"
        }
      ]
    },
    {
      "name": "t000012013",
      "lineContainers": [
        {
          "name": "name",
          "line": "一条　将輝"
        },
        {
          "name": "txt",
          "lines": [
            "ク　クリーンヒットか……\r\n",
            "さすがに効くな……"
          ]
        },
        {
          "name": "voice",
          "line": "voe00001201300"
        }
      ]
    },
    {
      "name": "t000012014",
      "lineContainers": [
        {
          "name": "name",
          "line": "服部刑部少丞範蔵"
        },
        {
          "name": "txt",
          "lines": [
            "（……鋭いビンタだな\r\n",
            "　お陰で意識が飛びそうに\r\n",
            "　なってしまった……）"
          ]
        },
        {
          "name": "voice",
          "line": "voe00001201400"
        }
      ]
    },
    {
      "name": "t000012015",
      "lineContainers": [
        {
          "name": "name",
          "line": "五十里　啓"
        },
        {
          "name": "voice",
          "line": "voe00001201500"
        }
      ]
    },
    {
      "name": "t000012016",
      "lineContainers": [
        {
          "name": "name",
          "line": "吉祥寺　真紅郎"
        },
        {
          "name": "txt",
          "lines": [
            "（……段々と\r\n",
            "　頬が腫れ上がってきた）"
          ]
        },
        {
          "name": "voice",
          "line": "voe00001201600"
        }
      ]
    }
  ]
}